pyts/__init__.py
pyts/base.py
pyts/approximation/__init__.py
pyts/approximation/dft.py
pyts/approximation/mcb.py
pyts/approximation/paa.py
pyts/approximation/sax.py
pyts/approximation/sfa.py
pyts/approximation/tests/__init__.py
pyts/approximation/tests/test_dft.py
pyts/approximation/tests/test_mcb.py
pyts/approximation/tests/test_paa.py
pyts/approximation/tests/test_sax.py
pyts/approximation/tests/test_sfa.py
pyts/bag_of_words/__init__.py
pyts/bag_of_words/bow.py
pyts/bag_of_words/tests/__init__.py
pyts/bag_of_words/tests/test_bow.py
pyts/classification/__init__.py
pyts/classification/bossvs.py
pyts/classification/knn.py
pyts/classification/learning_shapelets.py
pyts/classification/saxvsm.py
pyts/classification/time_series_forest.py
pyts/classification/tsbf.py
pyts/classification/tests/__init__.py
pyts/classification/tests/test_bossvs.py
pyts/classification/tests/test_knn.py
pyts/classification/tests/test_learning_shapelets.py
pyts/classification/tests/test_saxvsm.py
pyts/classification/tests/test_time_series_forest.py
pyts/classification/tests/test_tsbf.py
pyts/datasets/__init__.py
pyts/datasets/load.py
pyts/datasets/make.py
pyts/datasets/ucr.py
pyts/datasets/uea.py
pyts/datasets/cached_datasets/UCR/Coffee/Coffee.txt
pyts/datasets/cached_datasets/UCR/Coffee/Coffee_TEST.txt
pyts/datasets/cached_datasets/UCR/Coffee/Coffee_TRAIN.txt
pyts/datasets/cached_datasets/UCR/GunPoint/GunPoint.txt
pyts/datasets/cached_datasets/UCR/GunPoint/GunPoint_TEST.txt
pyts/datasets/cached_datasets/UCR/GunPoint/GunPoint_TRAIN.txt
pyts/datasets/cached_datasets/UCR/PigCVP/PigCVP.txt
pyts/datasets/cached_datasets/UCR/PigCVP/PigCVP_TEST.txt
pyts/datasets/cached_datasets/UCR/PigCVP/PigCVP_TRAIN.txt
pyts/datasets/cached_datasets/UEA/BasicMotions/BasicMotions.txt
pyts/datasets/cached_datasets/UEA/BasicMotions/BasicMotions_TEST.arff
pyts/datasets/cached_datasets/UEA/BasicMotions/BasicMotions_TRAIN.arff
pyts/datasets/info/ucr.pickle
pyts/datasets/info/uea.pickle
pyts/datasets/tests/__init__.py
pyts-0.13.0.dist-info/LICENSE.txt
pyts-0.13.0.dist-info/METADATA
pyts-0.13.0.dist-info/WHEEL
pyts-0.13.0.dist-info/top_level.txt
pyts-0.13.0.dist-info/RECORD
