Metadata-Version: 2.1
Name: pyts
Version: 0.13.0
Summary: A python package for time series classification
Home-page: https://github.com/johannfaouzi/pyts
Download-URL: https://github.com/johannfaouzi/pyts
Maintainer: Johann Faouzi
Maintainer-email: johann.faouzi@gmail.com
License: new BSD
Classifier: Development Status :: 3 - Alpha
Classifier: Intended Audience :: Science/Research
Classifier: Intended Audience :: Developers
Classifier: License :: OSI Approved
Classifier: Programming Language :: Python
Classifier: Topic :: Software Development
Classifier: Topic :: Scientific/Engineering
Classifier: Operating System :: Microsoft :: Windows
Classifier: Operating System :: POSIX
Classifier: Operating System :: Unix
Classifier: Operating System :: MacOS
Classifier: Programming Language :: Python :: 3.8
Classifier: Programming Language :: Python :: 3.9
Classifier: Programming Language :: Python :: 3.10
Classifier: Programming Language :: Python :: 3.11
License-File: LICENSE.txt
Requires-Dist: numpy (>=1.22.4)
Requires-Dist: scipy (>=1.8.1)
Requires-Dist: scikit-learn (>=1.2.0)
Requires-Dist: joblib (>=1.1.1)
Requires-Dist: numba (>=0.55.2)
Provides-Extra: docs
Requires-Dist: docutils (==0.14) ; extra == 'docs'
Requires-Dist: sphinx (==1.8.5) ; extra == 'docs'
Requires-Dist: sphinx-gallery ; extra == 'docs'
Requires-Dist: numpydoc ; extra == 'docs'
Requires-Dist: matplotlib ; extra == 'docs'
Requires-Dist: packaging ; extra == 'docs'
Provides-Extra: linting
Requires-Dist: flake8 ; extra == 'linting'
Provides-Extra: tests
Requires-Dist: pytest ; extra == 'tests'
Requires-Dist: pytest-cov ; extra == 'tests'
